MANIFEST.in
README.rst
impy.py
setup.py
impy.egg-info/PKG-INFO
impy.egg-info/SOURCES.txt
impy.egg-info/dependency_links.txt
impy.egg-info/entry_points.txt
impy.egg-info/requires.txt
impy.egg-info/top_level.txt
test/test_impy.py