Metadata-Version: 1.1
Name: impy
Version: 0.2.8.2
Summary: Integrated Metaomic Pipeline command-line utility.
Home-page: http://r3lab.uni.lu/web/imp
Author: Shaman Narayanasamy, Yohan Jarosz
Author-email: shaman.narayanasamy@uni.lu, yohan.jarosz@uni.lu
License: MIT
Keywords: metagenomics metatranscriptomics pipeline integrated ecosystems biology
Platform: UNKNOWN
Classifier: Environment :: Console
Classifier: Development Status :: 3 - Alpha
Classifier: Intended Audience :: Science/Research
Classifier: License :: OSI Approved :: MIT License
Classifier: Natural Language :: English
Classifier: Programming Language :: Python
Classifier: Topic :: Scientific/Engineering :: Bio-Informatics
Classifier: License :: OSI Approved :: BSD License
